FM15_transform/__init__.py
FM15_transform/bufr2geojson.py
FM15_transform/data2bufr.py
FM15_transform/metarDecoder/__init__.py
FM15_transform/metarDecoder/metarDecoders.py
FM15_transform/metarDecoder/tpg.py
FM15_transform/metarDecoder/xmlConfig.py
FM15_transform/metarDecoder/xmlUtilities.py
FM15_transform/resources/307051_mapping.json
FM15_transform/resources/__init__.py
FM15_transform/resources/station_list.csv
FM15_transform-0.0.19.dist-info/METADATA
FM15_transform-0.0.19.dist-info/WHEEL
FM15_transform-0.0.19.dist-info/entry_points.txt
FM15_transform-0.0.19.dist-info/top_level.txt
FM15_transform-0.0.19.dist-info/RECORD
